[
  {
    "title": "Idris Elba",
    "pictureUrl": "https://image.tmdb.org/t/p/w500/d9NkfCwczP0TjgrjpF94jF67SK8.jpg",
    "popularity": 0
  },
  {
    "title": "pepe",
    "pictureUrl": "https://image.tmdb.org/t/p/w500/d9NkfCwczP0TjgrjpF94jF67SK8.jpg",
    "popularity": 0
  },
  {
    "title": "Idris Elba",
    "pictureUrl": "https://image.tmdb.org/t/p/w500/d9NkfCwczP0TjgrjpF94jF67SK8.jpg",
    "popularity": 0
  },
  {
    "title": "Idris Elba",
    "pictureUrl": "https://image.tmdb.org/t/p/w500/d9NkfCwczP0TjgrjpF94jF67SK8.jpg",
    "popularity": 0
  }
]